MANIFEST.in
README.markdown
requirements.txt
setup.py
bin/__capn
bin/capn
capn/__init__.py
capn/config.py
capn/hooks.py
capn/paths.py
capn/util.py
capn.egg-info/PKG-INFO
capn.egg-info/SOURCES.txt
capn.egg-info/dependency_links.txt
capn.egg-info/requires.txt
capn.egg-info/top_level.txt