Metadata-Version: 1.1
Name: capn
Version: 1.0rc1
Summary: capn provides hooks on working-directory change.
Home-page: https://github.com/dustinlacewell/capn
Author: Dustin Lacewell
Author-email: dlacewell@gmail.com
License: UNKNOWN
Platform: UNKNOWN
Provides: capn
